minian_docker/__init__.py
minian_docker/agent.py
minian_docker/bin.py
minian_docker/docker.py
minian_docker/host_info.py
minian_docker/motd.py
minian_docker/version.py
minian_docker-0.1.3.dist-info/LICENSE
minian_docker-0.1.3.dist-info/METADATA
minian_docker-0.1.3.dist-info/WHEEL
minian_docker-0.1.3.dist-info/entry_points.txt
minian_docker-0.1.3.dist-info/top_level.txt
minian_docker-0.1.3.dist-info/RECORD
