Metadata-Version: 2.1
Name: minian-docker
Version: 0.1.3
Summary: MiniAn-docker is the package create environment of executiuon for MiniAn in Docker.
Home-page: https://github.com/masahito1997/minian-docker
Author: m11o
Author-email: velonica2227@outlook.jp
Maintainer: m11o
Maintainer-email: velonica2227@outlook.jp
License: GNU GPLv3
Keywords: minian,docker,minian-docker
Platform: UNKNOWN
Classifier: Programming Language :: Python :: 3
Classifier: Framework :: IPython
Classifier: Framework :: Jupyter
Classifier: Topic :: Utilities
License-File: LICENSE
